pioneer_sdk/__init__.py
pioneer_sdk/camera.py
pioneer_sdk/generic.py
pioneer_sdk/piosdk.py
pioneer_sdk/mavsub/ftp.py
pioneer_sdk/mavsub/wifi.py
pioneer_sdk/tools/lua.py
pioneer_sdk/tools/luac
pioneer_sdk/tools/luac.exe
pioneer_sdk-0.5.3.dist-info/LICENSE.txt
pioneer_sdk-0.5.3.dist-info/METADATA
pioneer_sdk-0.5.3.dist-info/WHEEL
pioneer_sdk-0.5.3.dist-info/top_level.txt
pioneer_sdk-0.5.3.dist-info/RECORD
