Metadata-Version: 2.1
Name: pioneer-sdk
Version: 0.5.3
Summary: Programming tools for programming geoscan pioneer drone
Home-page: https://github.com/geoscan/pioneer_sdk
Author: geoscan
Author-email: info@geoscan.aero
License: MIT
Keywords: mavlink,pioneer,geoscan
Platform: UNKNOWN
Classifier: Programming Language :: Python :: 3
Classifier: License :: OSI Approved :: MIT License
Classifier: Operating System :: OS Independent
Requires-Python: >=3.7
License-File: LICENSE.txt
Requires-Dist: pymavlink (==2.4.37)
Requires-Dist: pyserial (==3.5)
Requires-Dist: future (==0.18.3)
Requires-Dist: numpy
Requires-Dist: opencv-contrib-python (==4.7.0.72)
